ucal_client/__init__.py
ucal_client/base.py
ucal_client/client.py
ucal_client/_internal_grpc/__init__.py
ucal_client/_internal_grpc/server_pb2.py
ucal_client/_internal_grpc/server_pb2_grpc.py
ucal_client/test/__init__.py
ucal_client/test/test_ucal_client.py
ucal_client-0.6.0.dist-info/METADATA
ucal_client-0.6.0.dist-info/WHEEL
ucal_client-0.6.0.dist-info/top_level.txt
ucal_client-0.6.0.dist-info/RECORD
