Metadata-Version: 2.1
Name: ucal-client
Version: 0.6.0
Summary: Client for Ucal Manager Server
Home-page: https://bitbucket.com/zimka/ucal_client
Author: Boris Zimka, Igor Stepanenko
Author-email: zimka@phystech.edu, igor.stepanenko@phystech.edu
License: UNKNOWN
Platform: UNKNOWN
Classifier: Development Status :: 3 - Alpha
Classifier: Intended Audience :: End Users/Desktop
Classifier: Intended Audience :: Science/Research
Classifier: Operating System :: OS Independent
Classifier: Programming Language :: Python :: 3 :: Only
Classifier: Topic :: Scientific/Engineering
Requires-Python: >3.5.0
Requires-Dist: grpcio (>=1.23.0)
Requires-Dist: pandas (>=0.24.0)
Requires-Dist: grpcio-tools (>=1.23.0)
